.gitignore
MANIFEST.in
README.txt
setup.cfg
setup.py
collective/__init__.py
collective.portlet.usertrack.egg-info/PKG-INFO
collective.portlet.usertrack.egg-info/SOURCES.txt
collective.portlet.usertrack.egg-info/dependency_links.txt
collective.portlet.usertrack.egg-info/namespace_packages.txt
collective.portlet.usertrack.egg-info/not-zip-safe
collective.portlet.usertrack.egg-info/requires.txt
collective.portlet.usertrack.egg-info/top_level.txt
collective/portlet/__init__.py
collective/portlet/usertrack/__init__.py
collective/portlet/usertrack/configure.zcml
collective/portlet/usertrack/events.py
collective/portlet/usertrack/interfaces.py
collective/portlet/usertrack/storage.py
collective/portlet/usertrack/usertrack.css
collective/portlet/usertrack/usertrack.kss
collective/portlet/usertrack/usertrack.pt
collective/portlet/usertrack/usertrack.py
collective/portlet/usertrack/version.txt
collective/portlet/usertrack/i18n/collective.portlet.usertrack-es.po
collective/portlet/usertrack/i18n/collective.portlet.usertrack-fr.po
collective/portlet/usertrack/i18n/collective.portlet.usertrack.pot
collective/portlet/usertrack/profiles/default/cssregistry.xml
collective/portlet/usertrack/profiles/default/kssregistry.xml
collective/portlet/usertrack/profiles/default/metadata.xml
collective/portlet/usertrack/profiles/default/portlets.xml
collective/portlet/usertrack/tests/__init__.py
collective/portlet/usertrack/tests/base.py
collective/portlet/usertrack/tests/test_portlet.py
collective/portlet/usertrack/tests/test_storage.py
docs/HISTORY.txt
docs/INSTALL.txt
docs/LICENSE.GPL
docs/LICENSE.txt