Metadata-Version: 1.1
Name: collective.portlet.usertrack
Version: 1.1.1
Summary: User activity portlet
Home-page: http://pypi.python.org/pypi/collective.portlet.usertrack
Author: Wichert Akkerman
Author-email: wichert@wiggy.net
License: GPL
Keywords: user tracking plone
Platform: UNKNOWN
Classifier: Framework :: Plone
Classifier: Programming Language :: Python
Classifier: Programming Language :: Python :: 2.6
Classifier: Programming Language :: Python :: 2.7
Classifier: Topic :: Software Development :: Libraries :: Python Modules
